setup.py
src/django_slim.egg-info/PKG-INFO
src/django_slim.egg-info/SOURCES.txt
src/django_slim.egg-info/dependency_links.txt
src/django_slim.egg-info/requires.txt
src/django_slim.egg-info/top_level.txt
src/slim/__init__.py
src/slim/admin.py
src/slim/conf.py
src/slim/defaults.py
src/slim/exceptions.py
src/slim/helpers.py
src/slim/monkey_patches.py
src/slim/settings.py
src/slim/tests.py
src/slim/translations.py
src/slim/utils.py
src/slim/models/__init__.py
src/slim/models/decorators.py
src/slim/models/fields.py
src/slim/templatetags/__init__.py
src/slim/templatetags/slim_tags.py